bbstrading/__init__.cp311-win_amd64.pyd
bbstrading/__main__.cp311-win_amd64.pyd
bbstrading/backtests.cp311-win_amd64.pyd
bbstrading/brokers.cp311-win_amd64.pyd
bbstrading/config.cp311-win_amd64.pyd
bbstrading/execution.cp311-win_amd64.pyd
bbstrading/scripts.cp311-win_amd64.pyd
bbstrading/strategies.cp311-win_amd64.pyd
bbstrading/utils.cp311-win_amd64.pyd
bbstrading-0.1.31.dist-info/LICENSE.rst
bbstrading-0.1.31.dist-info/METADATA
bbstrading-0.1.31.dist-info/WHEEL
bbstrading-0.1.31.dist-info/entry_points.txt
bbstrading-0.1.31.dist-info/top_level.txt
bbstrading-0.1.31.dist-info/RECORD
