Metadata-Version: 2.2
Name: bbstrading
Version: 0.1.31
Summary: Trading strategies development, backtesting and live Execution
Author: Bertin Balouki SIMYELI
Author-email: <bertin@bbstrader.com>
Maintainer: Bertin Balouki SIMYELI
License: Proprietary, All Rights Reserved
License-File: LICENSE.rst
Requires-Dist: bbstrader
Requires-Dist: colorama
Requires-Dist: pyfiglet
Dynamic: author
Dynamic: author-email
Dynamic: description
Dynamic: description-content-type
Dynamic: license
Dynamic: maintainer
Dynamic: requires-dist
Dynamic: summary
